{"1":{"2":{"name":"중식","people":"797","menus":[{"name":"유기농통밀밥","allergy":[6]},{"name":"들깨새송이미역국"},{"name":"숙주김나물"},{"name":"양배추견과샐러드\/키위드레싱","allergy":[1,2,5,6,14]},{"name":"통등심돈까스\/브라운소스","allergy":[1,2,5,6,10,11,12,13,16,18]},{"name":"배추김치","allergy":[9]},{"name":"엔요요구르트*","allergy":[2]}],"origin":[{"name":"쇠고기(종류)","origin":"국내산(한우)"},{"name":"쇠고기 식육가공품","origin":"국내산"},{"name":"돼지고기","origin":"국내산"},{"name":"돼지고기 식육가공품","origin":"국내산"},{"name":"닭고기","origin":"국내산"},{"name":"닭고기 식육가공품","origin":"국내산"},{"name":"오리고기","origin":"국내산"},{"name":"오리고기 가공품","origin":"국내산"},{"name":"양고기","origin":"해당없음"},{"name":"양고기 식육가공품","origin":"사용안함"},{"name":"쌀","origin":"국내산"},{"name":"쌀 가공품","origin":"국내산"},{"name":"배추","origin":"국내산"},{"name":"배추 가공품","origin":"국내산"},{"name":"고춧가루","origin":"국내산"},{"name":"고춧가루 가공품","origin":"국내산"},{"name":"콩","origin":"국내산"},{"name":"콩 가공품","origin":"국내산"},{"name":"넙치","origin":"국내산"},{"name":"넙치 수산가공품","origin":"국내산"},{"name":"조피볼락 수산가공품","origin":"국내산"},{"name":"조피볼락","origin":"국내산"},{"name":"참돔","origin":"국내산"},{"name":"참돔 수산가공품","origin":"국내산"},{"name":"미꾸라지","origin":"국내산"},{"name":"미꾸라지 수산가공품","origin":"국내산"},{"name":"뱀장어","origin":"사용안함"},{"name":"뱀장어 수산가공품","origin":"사용안함"},{"name":"낙지","origin":"중국산"},{"name":"낙지 수산가공품","origin":"사용안함"},{"name":"명태","origin":"미국산 ,러시아산"},{"name":"명태 수산가공품","origin":"미국산 ,러시아산"},{"name":"고등어","origin":"국내산"},{"name":"고등어 수산가공품","origin":"국내산"},{"name":"갈치","origin":"중국산"},{"name":"갈치 수산가공품","origin":"해당없음"},{"name":"오징어","origin":"국내산"},{"name":"오징어 수산가공품","origin":"국내산"},{"name":"꽃게 수산가공품","origin":"해당없음"},{"name":"꽃게","origin":"국내산"},{"name":"참조기","origin":"국내산"},{"name":"참조기 수산가공품","origin":"해당없음"},{"name":"다랑어","origin":"국내산"},{"name":"다랑어 수산가공품","origin":"해당없음"},{"name":"아귀","origin":"국내산"},{"name":"아귀 수산가공품","origin":"해당없음"},{"name":"주꾸미","origin":"국내산"},{"name":"주꾸미 수산가공품","origin":"해당없음"},{"name":"가리비","origin":"국내산"},{"name":"가리비 수산가공품","origin":"해당없음"},{"name":"우렁쉥이","origin":"국내산"},{"name":"우렁쉥이 수산가공품","origin":"해당없음"},{"name":"전복","origin":"국내산"},{"name":"전복 수산가공품","origin":"해당없음"},{"name":"방어","origin":"국내산"},{"name":"방어 수산가공품","origin":"해당없음"},{"name":"부세","origin":"국내산"},{"name":"부세 수산가공품","origin":"해당없음"},{"name":"비고","origin":""}],"calorie":"853.3 Kcal","nutrition":[{"name":"탄수화물","unit":"g","value":"98.7"},{"name":"단백질","unit":"g","value":"18.9"},{"name":"지방","unit":"g","value":"42.5"},{"name":"비타민A","unit":"R.E","value":"47.5"},{"name":"티아민","unit":"mg","value":"0.7"},{"name":"리보플라빈","unit":"mg","value":"0.3"},{"name":"비타민C","unit":"mg","value":"10.4"},{"name":"칼슘","unit":"mg","value":"185.5"},{"name":"철분","unit":"mg","value":"2.9"}],"modifiedAt":1759330800}},"2":{"2":{"name":"중식","people":"797","menus":[{"name":"유기농클로렐라밥"},{"name":"모듬어묵국","allergy":[1,5,6,13]},{"name":"도라지오이초무침","allergy":[5,6,13]},{"name":"돈육콩나물볶음","allergy":[5,6,10]},{"name":"김치치즈전","allergy":[1,2,6,9,17]},{"name":"깍두기","allergy":[9]},{"name":"송편"},{"name":"라임레몬쥬스","allergy":[13]}],"origin":[{"name":"쇠고기(종류)","origin":"국내산(한우)"},{"name":"쇠고기 식육가공품","origin":"국내산"},{"name":"돼지고기","origin":"국내산"},{"name":"돼지고기 식육가공품","origin":"국내산"},{"name":"닭고기","origin":"국내산"},{"name":"닭고기 식육가공품","origin":"국내산"},{"name":"오리고기","origin":"국내산"},{"name":"오리고기 가공품","origin":"국내산"},{"name":"양고기","origin":"해당없음"},{"name":"양고기 식육가공품","origin":"사용안함"},{"name":"쌀","origin":"국내산"},{"name":"쌀 가공품","origin":"국내산"},{"name":"배추","origin":"국내산"},{"name":"배추 가공품","origin":"국내산"},{"name":"고춧가루","origin":"국내산"},{"name":"고춧가루 가공품","origin":"국내산"},{"name":"콩","origin":"국내산"},{"name":"콩 가공품","origin":"국내산"},{"name":"넙치","origin":"국내산"},{"name":"넙치 수산가공품","origin":"국내산"},{"name":"조피볼락 수산가공품","origin":"국내산"},{"name":"조피볼락","origin":"국내산"},{"name":"참돔","origin":"국내산"},{"name":"참돔 수산가공품","origin":"국내산"},{"name":"미꾸라지","origin":"국내산"},{"name":"미꾸라지 수산가공품","origin":"국내산"},{"name":"뱀장어","origin":"사용안함"},{"name":"뱀장어 수산가공품","origin":"사용안함"},{"name":"낙지","origin":"중국산"},{"name":"낙지 수산가공품","origin":"사용안함"},{"name":"명태","origin":"미국산 ,러시아산"},{"name":"명태 수산가공품","origin":"미국산 ,러시아산"},{"name":"고등어","origin":"국내산"},{"name":"고등어 수산가공품","origin":"국내산"},{"name":"갈치","origin":"중국산"},{"name":"갈치 수산가공품","origin":"해당없음"},{"name":"오징어","origin":"국내산"},{"name":"오징어 수산가공품","origin":"국내산"},{"name":"꽃게 수산가공품","origin":"해당없음"},{"name":"꽃게","origin":"국내산"},{"name":"참조기","origin":"국내산"},{"name":"참조기 수산가공품","origin":"해당없음"},{"name":"다랑어","origin":"국내산"},{"name":"다랑어 수산가공품","origin":"해당없음"},{"name":"아귀","origin":"국내산"},{"name":"아귀 수산가공품","origin":"해당없음"},{"name":"주꾸미","origin":"국내산"},{"name":"주꾸미 수산가공품","origin":"해당없음"},{"name":"가리비","origin":"국내산"},{"name":"가리비 수산가공품","origin":"해당없음"},{"name":"우렁쉥이","origin":"국내산"},{"name":"우렁쉥이 수산가공품","origin":"해당없음"},{"name":"전복","origin":"국내산"},{"name":"전복 수산가공품","origin":"해당없음"},{"name":"방어","origin":"국내산"},{"name":"방어 수산가공품","origin":"해당없음"},{"name":"부세","origin":"국내산"},{"name":"부세 수산가공품","origin":"해당없음"},{"name":"비고","origin":""}],"calorie":"857.7 Kcal","nutrition":[{"name":"탄수화물","unit":"g","value":"129.6"},{"name":"단백질","unit":"g","value":"44.0"},{"name":"지방","unit":"g","value":"17.4"},{"name":"비타민A","unit":"R.E","value":"78.5"},{"name":"티아민","unit":"mg","value":"0.9"},{"name":"리보플라빈","unit":"mg","value":"0.5"},{"name":"비타민C","unit":"mg","value":"45.1"},{"name":"칼슘","unit":"mg","value":"211.5"},{"name":"철분","unit":"mg","value":"3.0"}],"modifiedAt":1759330800}},"13":{"2":{"name":"중식","people":"797","menus":[{"name":"유기농현미밥"},{"name":"다슬기수제비탕","allergy":[5,6]},{"name":"매콤돼지갈비찜","allergy":[5,6,10,13,18]},{"name":"사과치커리초무침","allergy":[13]},{"name":"두부담은돈저냐","allergy":[1,2,5,6,15,16,18]},{"name":"배추김치","allergy":[9]},{"name":"스위트맘 망고푸딩"}],"origin":[{"name":"쇠고기(종류)","origin":"국내산(한우)"},{"name":"쇠고기 식육가공품","origin":"국내산"},{"name":"돼지고기","origin":"국내산"},{"name":"돼지고기 식육가공품","origin":"국내산"},{"name":"닭고기","origin":"국내산"},{"name":"닭고기 식육가공품","origin":"국내산"},{"name":"오리고기","origin":"국내산"},{"name":"오리고기 가공품","origin":"국내산"},{"name":"양고기","origin":"해당없음"},{"name":"양고기 식육가공품","origin":"사용안함"},{"name":"쌀","origin":"국내산"},{"name":"쌀 가공품","origin":"국내산"},{"name":"배추","origin":"국내산"},{"name":"배추 가공품","origin":"국내산"},{"name":"고춧가루","origin":"국내산"},{"name":"고춧가루 가공품","origin":"국내산"},{"name":"콩","origin":"국내산"},{"name":"콩 가공품","origin":"국내산"},{"name":"넙치","origin":"국내산"},{"name":"넙치 수산가공품","origin":"국내산"},{"name":"조피볼락 수산가공품","origin":"국내산"},{"name":"조피볼락","origin":"국내산"},{"name":"참돔","origin":"국내산"},{"name":"참돔 수산가공품","origin":"국내산"},{"name":"미꾸라지","origin":"국내산"},{"name":"미꾸라지 수산가공품","origin":"국내산"},{"name":"뱀장어","origin":"사용안함"},{"name":"뱀장어 수산가공품","origin":"사용안함"},{"name":"낙지","origin":"중국산"},{"name":"낙지 수산가공품","origin":"사용안함"},{"name":"명태","origin":"미국산 ,러시아산"},{"name":"명태 수산가공품","origin":"미국산 ,러시아산"},{"name":"고등어","origin":"국내산"},{"name":"고등어 수산가공품","origin":"국내산"},{"name":"갈치","origin":"중국산"},{"name":"갈치 수산가공품","origin":"해당없음"},{"name":"오징어","origin":"국내산"},{"name":"오징어 수산가공품","origin":"국내산"},{"name":"꽃게 수산가공품","origin":"해당없음"},{"name":"꽃게","origin":"국내산"},{"name":"참조기","origin":"국내산"},{"name":"참조기 수산가공품","origin":"해당없음"},{"name":"다랑어","origin":"국내산"},{"name":"다랑어 수산가공품","origin":"해당없음"},{"name":"아귀","origin":"국내산"},{"name":"아귀 수산가공품","origin":"해당없음"},{"name":"주꾸미","origin":"국내산"},{"name":"주꾸미 수산가공품","origin":"해당없음"},{"name":"가리비","origin":"국내산"},{"name":"가리비 수산가공품","origin":"해당없음"},{"name":"우렁쉥이","origin":"국내산"},{"name":"우렁쉥이 수산가공품","origin":"해당없음"},{"name":"전복","origin":"국내산"},{"name":"전복 수산가공품","origin":"해당없음"},{"name":"방어","origin":"국내산"},{"name":"방어 수산가공품","origin":"해당없음"},{"name":"부세","origin":"국내산"},{"name":"부세 수산가공품","origin":"해당없음"},{"name":"비고","origin":""}],"calorie":"901.6 Kcal","nutrition":[{"name":"탄수화물","unit":"g","value":"106.9"},{"name":"단백질","unit":"g","value":"36.0"},{"name":"지방","unit":"g","value":"34.2"},{"name":"비타민A","unit":"R.E","value":"98.5"},{"name":"티아민","unit":"mg","value":"1.0"},{"name":"리보플라빈","unit":"mg","value":"0.5"},{"name":"비타민C","unit":"mg","value":"11.5"},{"name":"칼슘","unit":"mg","value":"84.1"},{"name":"철분","unit":"mg","value":"2.1"}],"modifiedAt":1759330800}},"14":{"2":{"name":"중식","people":"797","menus":[{"name":"유기농청차조밥"},{"name":"잔치국수","allergy":[1,5,6]},{"name":"단호박닭조림","allergy":[5,6,13,15]},{"name":"김자반실파무침","allergy":[5,6]},{"name":"온두부&볶음김치","allergy":[5,9,10]},{"name":"감귤한라봉쥬스","allergy":[13]}],"origin":[{"name":"쇠고기(종류)","origin":"국내산(한우)"},{"name":"쇠고기 식육가공품","origin":"국내산"},{"name":"돼지고기","origin":"국내산"},{"name":"돼지고기 식육가공품","origin":"국내산"},{"name":"닭고기","origin":"국내산"},{"name":"닭고기 식육가공품","origin":"국내산"},{"name":"오리고기","origin":"국내산"},{"name":"오리고기 가공품","origin":"국내산"},{"name":"양고기","origin":"해당없음"},{"name":"양고기 식육가공품","origin":"사용안함"},{"name":"쌀","origin":"국내산"},{"name":"쌀 가공품","origin":"국내산"},{"name":"배추","origin":"국내산"},{"name":"배추 가공품","origin":"국내산"},{"name":"고춧가루","origin":"국내산"},{"name":"고춧가루 가공품","origin":"국내산"},{"name":"콩","origin":"국내산"},{"name":"콩 가공품","origin":"국내산"},{"name":"넙치","origin":"국내산"},{"name":"넙치 수산가공품","origin":"국내산"},{"name":"조피볼락 수산가공품","origin":"국내산"},{"name":"조피볼락","origin":"국내산"},{"name":"참돔","origin":"국내산"},{"name":"참돔 수산가공품","origin":"국내산"},{"name":"미꾸라지","origin":"국내산"},{"name":"미꾸라지 수산가공품","origin":"국내산"},{"name":"뱀장어","origin":"사용안함"},{"name":"뱀장어 수산가공품","origin":"사용안함"},{"name":"낙지","origin":"중국산"},{"name":"낙지 수산가공품","origin":"사용안함"},{"name":"명태","origin":"미국산 ,러시아산"},{"name":"명태 수산가공품","origin":"미국산 ,러시아산"},{"name":"고등어","origin":"국내산"},{"name":"고등어 수산가공품","origin":"국내산"},{"name":"갈치","origin":"중국산"},{"name":"갈치 수산가공품","origin":"해당없음"},{"name":"오징어","origin":"국내산"},{"name":"오징어 수산가공품","origin":"국내산"},{"name":"꽃게 수산가공품","origin":"해당없음"},{"name":"꽃게","origin":"국내산"},{"name":"참조기","origin":"국내산"},{"name":"참조기 수산가공품","origin":"해당없음"},{"name":"다랑어","origin":"국내산"},{"name":"다랑어 수산가공품","origin":"해당없음"},{"name":"아귀","origin":"국내산"},{"name":"아귀 수산가공품","origin":"해당없음"},{"name":"주꾸미","origin":"국내산"},{"name":"주꾸미 수산가공품","origin":"해당없음"},{"name":"가리비","origin":"국내산"},{"name":"가리비 수산가공품","origin":"해당없음"},{"name":"우렁쉥이","origin":"국내산"},{"name":"우렁쉥이 수산가공품","origin":"해당없음"},{"name":"전복","origin":"국내산"},{"name":"전복 수산가공품","origin":"해당없음"},{"name":"방어","origin":"국내산"},{"name":"방어 수산가공품","origin":"해당없음"},{"name":"부세","origin":"국내산"},{"name":"부세 수산가공품","origin":"해당없음"},{"name":"비고","origin":""}],"calorie":"785.3 Kcal","nutrition":[{"name":"탄수화물","unit":"g","value":"113.4"},{"name":"단백질","unit":"g","value":"40.1"},{"name":"지방","unit":"g","value":"18.2"},{"name":"비타민A","unit":"R.E","value":"177.5"},{"name":"티아민","unit":"mg","value":"0.7"},{"name":"리보플라빈","unit":"mg","value":"0.8"},{"name":"비타민C","unit":"mg","value":"29.2"},{"name":"칼슘","unit":"mg","value":"168.8"},{"name":"철분","unit":"mg","value":"4.0"}],"modifiedAt":1759330800}},"15":{"2":{"name":"중식","people":"797","menus":[{"name":"김가루주먹밥"},{"name":"유부된장국","allergy":[5,6]},{"name":"콩나물무침(자율)","allergy":[5]},{"name":"브로콜리다시마초무침","allergy":[5,6,13]},{"name":"배추김치","allergy":[9]},{"name":"청포도쥬스","allergy":[13]},{"name":"스테이크치킨버거","allergy":[1,2,5,6,12,13,15]}],"origin":[{"name":"쇠고기(종류)","origin":"국내산(한우)"},{"name":"쇠고기 식육가공품","origin":"국내산"},{"name":"돼지고기","origin":"국내산"},{"name":"돼지고기 식육가공품","origin":"국내산"},{"name":"닭고기","origin":"국내산"},{"name":"닭고기 식육가공품","origin":"국내산"},{"name":"오리고기","origin":"국내산"},{"name":"오리고기 가공품","origin":"국내산"},{"name":"양고기","origin":"해당없음"},{"name":"양고기 식육가공품","origin":"사용안함"},{"name":"쌀","origin":"국내산"},{"name":"쌀 가공품","origin":"국내산"},{"name":"배추","origin":"국내산"},{"name":"배추 가공품","origin":"국내산"},{"name":"고춧가루","origin":"국내산"},{"name":"고춧가루 가공품","origin":"국내산"},{"name":"콩","origin":"국내산"},{"name":"콩 가공품","origin":"국내산"},{"name":"넙치","origin":"국내산"},{"name":"넙치 수산가공품","origin":"국내산"},{"name":"조피볼락 수산가공품","origin":"국내산"},{"name":"조피볼락","origin":"국내산"},{"name":"참돔","origin":"국내산"},{"name":"참돔 수산가공품","origin":"국내산"},{"name":"미꾸라지","origin":"국내산"},{"name":"미꾸라지 수산가공품","origin":"국내산"},{"name":"뱀장어","origin":"사용안함"},{"name":"뱀장어 수산가공품","origin":"사용안함"},{"name":"낙지","origin":"중국산"},{"name":"낙지 수산가공품","origin":"사용안함"},{"name":"명태","origin":"미국산 ,러시아산"},{"name":"명태 수산가공품","origin":"미국산 ,러시아산"},{"name":"고등어","origin":"국내산"},{"name":"고등어 수산가공품","origin":"국내산"},{"name":"갈치","origin":"중국산"},{"name":"갈치 수산가공품","origin":"해당없음"},{"name":"오징어","origin":"국내산"},{"name":"오징어 수산가공품","origin":"국내산"},{"name":"꽃게 수산가공품","origin":"해당없음"},{"name":"꽃게","origin":"국내산"},{"name":"참조기","origin":"국내산"},{"name":"참조기 수산가공품","origin":"해당없음"},{"name":"다랑어","origin":"국내산"},{"name":"다랑어 수산가공품","origin":"해당없음"},{"name":"아귀","origin":"국내산"},{"name":"아귀 수산가공품","origin":"해당없음"},{"name":"주꾸미","origin":"국내산"},{"name":"주꾸미 수산가공품","origin":"해당없음"},{"name":"가리비","origin":"국내산"},{"name":"가리비 수산가공품","origin":"해당없음"},{"name":"우렁쉥이","origin":"국내산"},{"name":"우렁쉥이 수산가공품","origin":"해당없음"},{"name":"전복","origin":"국내산"},{"name":"전복 수산가공품","origin":"해당없음"},{"name":"방어","origin":"국내산"},{"name":"방어 수산가공품","origin":"해당없음"},{"name":"부세","origin":"국내산"},{"name":"부세 수산가공품","origin":"해당없음"},{"name":"비고","origin":""}],"calorie":"749.6 Kcal","nutrition":[{"name":"탄수화물","unit":"g","value":"99.0"},{"name":"단백질","unit":"g","value":"34.8"},{"name":"지방","unit":"g","value":"22.2"},{"name":"비타민A","unit":"R.E","value":"106.2"},{"name":"티아민","unit":"mg","value":"0.6"},{"name":"리보플라빈","unit":"mg","value":"0.5"},{"name":"비타민C","unit":"mg","value":"10.6"},{"name":"칼슘","unit":"mg","value":"289.8"},{"name":"철분","unit":"mg","value":"3.9"}],"modifiedAt":1759330800}},"16":{"2":{"name":"중식","people":"797","menus":[{"name":"유기농홍국밥"},{"name":"북어두부콩나물국","allergy":[5]},{"name":"마파두부","allergy":[5,6,10,12,13,18]},{"name":"상추부추들깨무침","allergy":[5,6,13]},{"name":"배추김치","allergy":[9]},{"name":"플레인요거트","allergy":[2]},{"name":"뱅글뱅글찰도그롤","allergy":[2,5,6,10,12,15]}],"origin":[{"name":"쇠고기(종류)","origin":"국내산(한우)"},{"name":"쇠고기 식육가공품","origin":"국내산"},{"name":"돼지고기","origin":"국내산"},{"name":"돼지고기 식육가공품","origin":"국내산"},{"name":"닭고기","origin":"국내산"},{"name":"닭고기 식육가공품","origin":"국내산"},{"name":"오리고기","origin":"국내산"},{"name":"오리고기 가공품","origin":"국내산"},{"name":"양고기","origin":"해당없음"},{"name":"양고기 식육가공품","origin":"사용안함"},{"name":"쌀","origin":"국내산"},{"name":"쌀 가공품","origin":"국내산"},{"name":"배추","origin":"국내산"},{"name":"배추 가공품","origin":"국내산"},{"name":"고춧가루","origin":"국내산"},{"name":"고춧가루 가공품","origin":"국내산"},{"name":"콩","origin":"국내산"},{"name":"콩 가공품","origin":"국내산"},{"name":"넙치","origin":"국내산"},{"name":"넙치 수산가공품","origin":"국내산"},{"name":"조피볼락 수산가공품","origin":"국내산"},{"name":"조피볼락","origin":"국내산"},{"name":"참돔","origin":"국내산"},{"name":"참돔 수산가공품","origin":"국내산"},{"name":"미꾸라지","origin":"국내산"},{"name":"미꾸라지 수산가공품","origin":"국내산"},{"name":"뱀장어","origin":"사용안함"},{"name":"뱀장어 수산가공품","origin":"사용안함"},{"name":"낙지","origin":"중국산"},{"name":"낙지 수산가공품","origin":"사용안함"},{"name":"명태","origin":"미국산 ,러시아산"},{"name":"명태 수산가공품","origin":"미국산 ,러시아산"},{"name":"고등어","origin":"국내산"},{"name":"고등어 수산가공품","origin":"국내산"},{"name":"갈치","origin":"중국산"},{"name":"갈치 수산가공품","origin":"해당없음"},{"name":"오징어","origin":"국내산"},{"name":"오징어 수산가공품","origin":"국내산"},{"name":"꽃게 수산가공품","origin":"해당없음"},{"name":"꽃게","origin":"국내산"},{"name":"참조기","origin":"국내산"},{"name":"참조기 수산가공품","origin":"해당없음"},{"name":"다랑어","origin":"국내산"},{"name":"다랑어 수산가공품","origin":"해당없음"},{"name":"아귀","origin":"국내산"},{"name":"아귀 수산가공품","origin":"해당없음"},{"name":"주꾸미","origin":"국내산"},{"name":"주꾸미 수산가공품","origin":"해당없음"},{"name":"가리비","origin":"국내산"},{"name":"가리비 수산가공품","origin":"해당없음"},{"name":"우렁쉥이","origin":"국내산"},{"name":"우렁쉥이 수산가공품","origin":"해당없음"},{"name":"전복","origin":"국내산"},{"name":"전복 수산가공품","origin":"해당없음"},{"name":"방어","origin":"국내산"},{"name":"방어 수산가공품","origin":"해당없음"},{"name":"부세","origin":"국내산"},{"name":"부세 수산가공품","origin":"해당없음"},{"name":"비고","origin":""}],"calorie":"781.9 Kcal","nutrition":[{"name":"탄수화물","unit":"g","value":"115.1"},{"name":"단백질","unit":"g","value":"30.0"},{"name":"지방","unit":"g","value":"22.4"},{"name":"비타민A","unit":"R.E","value":"117.3"},{"name":"티아민","unit":"mg","value":"0.4"},{"name":"리보플라빈","unit":"mg","value":"0.5"},{"name":"비타민C","unit":"mg","value":"16.0"},{"name":"칼슘","unit":"mg","value":"371.9"},{"name":"철분","unit":"mg","value":"3.1"}],"modifiedAt":1759330800}},"17":{"2":{"name":"중식","people":"797","menus":[{"name":"친환경찰현미밥"},{"name":"건시래기들깨된장국","allergy":[5,6]},{"name":"젤리양상추샐러드","allergy":[1,2,5,6,12]},{"name":"숯불향오리불고기","allergy":[5,6,12,13]},{"name":"배추김치","allergy":[9]},{"name":"식물성유산균요구르트","allergy":[2]},{"name":"파인불고기피자","allergy":[1,2,5,6,10,12,13,15,16]}],"origin":[{"name":"쇠고기(종류)","origin":"국내산(한우)"},{"name":"쇠고기 식육가공품","origin":"국내산"},{"name":"돼지고기","origin":"국내산"},{"name":"돼지고기 식육가공품","origin":"국내산"},{"name":"닭고기","origin":"국내산"},{"name":"닭고기 식육가공품","origin":"국내산"},{"name":"오리고기","origin":"국내산"},{"name":"오리고기 가공품","origin":"국내산"},{"name":"양고기","origin":"해당없음"},{"name":"양고기 식육가공품","origin":"사용안함"},{"name":"쌀","origin":"국내산"},{"name":"쌀 가공품","origin":"국내산"},{"name":"배추","origin":"국내산"},{"name":"배추 가공품","origin":"국내산"},{"name":"고춧가루","origin":"국내산"},{"name":"고춧가루 가공품","origin":"국내산"},{"name":"콩","origin":"국내산"},{"name":"콩 가공품","origin":"국내산"},{"name":"넙치","origin":"국내산"},{"name":"넙치 수산가공품","origin":"국내산"},{"name":"조피볼락 수산가공품","origin":"국내산"},{"name":"조피볼락","origin":"국내산"},{"name":"참돔","origin":"국내산"},{"name":"참돔 수산가공품","origin":"국내산"},{"name":"미꾸라지","origin":"국내산"},{"name":"미꾸라지 수산가공품","origin":"국내산"},{"name":"뱀장어","origin":"사용안함"},{"name":"뱀장어 수산가공품","origin":"사용안함"},{"name":"낙지","origin":"중국산"},{"name":"낙지 수산가공품","origin":"사용안함"},{"name":"명태","origin":"미국산 ,러시아산"},{"name":"명태 수산가공품","origin":"미국산 ,러시아산"},{"name":"고등어","origin":"국내산"},{"name":"고등어 수산가공품","origin":"국내산"},{"name":"갈치","origin":"중국산"},{"name":"갈치 수산가공품","origin":"해당없음"},{"name":"오징어","origin":"국내산"},{"name":"오징어 수산가공품","origin":"국내산"},{"name":"꽃게 수산가공품","origin":"해당없음"},{"name":"꽃게","origin":"국내산"},{"name":"참조기","origin":"국내산"},{"name":"참조기 수산가공품","origin":"해당없음"},{"name":"다랑어","origin":"국내산"},{"name":"다랑어 수산가공품","origin":"해당없음"},{"name":"아귀","origin":"국내산"},{"name":"아귀 수산가공품","origin":"해당없음"},{"name":"주꾸미","origin":"국내산"},{"name":"주꾸미 수산가공품","origin":"해당없음"},{"name":"가리비","origin":"국내산"},{"name":"가리비 수산가공품","origin":"해당없음"},{"name":"우렁쉥이","origin":"국내산"},{"name":"우렁쉥이 수산가공품","origin":"해당없음"},{"name":"전복","origin":"국내산"},{"name":"전복 수산가공품","origin":"해당없음"},{"name":"방어","origin":"국내산"},{"name":"방어 수산가공품","origin":"해당없음"},{"name":"부세","origin":"국내산"},{"name":"부세 수산가공품","origin":"해당없음"},{"name":"비고","origin":""}],"calorie":"979.1 Kcal","nutrition":[{"name":"탄수화물","unit":"g","value":"125.8"},{"name":"단백질","unit":"g","value":"36.4"},{"name":"지방","unit":"g","value":"36.1"},{"name":"비타민A","unit":"R.E","value":"150.0"},{"name":"티아민","unit":"mg","value":"0.7"},{"name":"리보플라빈","unit":"mg","value":"0.8"},{"name":"비타민C","unit":"mg","value":"14.4"},{"name":"칼슘","unit":"mg","value":"381.9"},{"name":"철분","unit":"mg","value":"4.0"}],"modifiedAt":1759330800}},"20":{"2":{"name":"중식","people":"797","menus":[{"name":"유기농보리밥"},{"name":"건새우아욱국","allergy":[5,6,9]},{"name":"비빔면(옥수수면)","allergy":[5,6,13]},{"name":"허브소시지채소볶음","allergy":[1,2,5,6,10,12,15,16]},{"name":"구이김"},{"name":"교자만두","allergy":[1,5,6,10,15,16,18]},{"name":"배추김치","allergy":[9]}],"origin":[{"name":"쇠고기(종류)","origin":"국내산(한우)"},{"name":"쇠고기 식육가공품","origin":"국내산"},{"name":"돼지고기","origin":"국내산"},{"name":"돼지고기 식육가공품","origin":"국내산"},{"name":"닭고기","origin":"국내산"},{"name":"닭고기 식육가공품","origin":"국내산"},{"name":"오리고기","origin":"국내산"},{"name":"오리고기 가공품","origin":"국내산"},{"name":"양고기","origin":"해당없음"},{"name":"양고기 식육가공품","origin":"사용안함"},{"name":"쌀","origin":"국내산"},{"name":"쌀 가공품","origin":"국내산"},{"name":"배추","origin":"국내산"},{"name":"배추 가공품","origin":"국내산"},{"name":"고춧가루","origin":"국내산"},{"name":"고춧가루 가공품","origin":"국내산"},{"name":"콩","origin":"국내산"},{"name":"콩 가공품","origin":"국내산"},{"name":"넙치","origin":"국내산"},{"name":"넙치 수산가공품","origin":"국내산"},{"name":"조피볼락 수산가공품","origin":"국내산"},{"name":"조피볼락","origin":"국내산"},{"name":"참돔","origin":"국내산"},{"name":"참돔 수산가공품","origin":"국내산"},{"name":"미꾸라지","origin":"국내산"},{"name":"미꾸라지 수산가공품","origin":"국내산"},{"name":"뱀장어","origin":"사용안함"},{"name":"뱀장어 수산가공품","origin":"사용안함"},{"name":"낙지","origin":"중국산"},{"name":"낙지 수산가공품","origin":"사용안함"},{"name":"명태","origin":"미국산 ,러시아산"},{"name":"명태 수산가공품","origin":"미국산 ,러시아산"},{"name":"고등어","origin":"국내산"},{"name":"고등어 수산가공품","origin":"국내산"},{"name":"갈치","origin":"중국산"},{"name":"갈치 수산가공품","origin":"해당없음"},{"name":"오징어","origin":"국내산"},{"name":"오징어 수산가공품","origin":"국내산"},{"name":"꽃게 수산가공품","origin":"해당없음"},{"name":"꽃게","origin":"국내산"},{"name":"참조기","origin":"국내산"},{"name":"참조기 수산가공품","origin":"해당없음"},{"name":"다랑어","origin":"국내산"},{"name":"다랑어 수산가공품","origin":"해당없음"},{"name":"아귀","origin":"국내산"},{"name":"아귀 수산가공품","origin":"해당없음"},{"name":"주꾸미","origin":"국내산"},{"name":"주꾸미 수산가공품","origin":"해당없음"},{"name":"가리비","origin":"국내산"},{"name":"가리비 수산가공품","origin":"해당없음"},{"name":"우렁쉥이","origin":"국내산"},{"name":"우렁쉥이 수산가공품","origin":"해당없음"},{"name":"전복","origin":"국내산"},{"name":"전복 수산가공품","origin":"해당없음"},{"name":"방어","origin":"국내산"},{"name":"방어 수산가공품","origin":"해당없음"},{"name":"부세","origin":"국내산"},{"name":"부세 수산가공품","origin":"해당없음"},{"name":"비고","origin":""}],"calorie":"789.9 Kcal","nutrition":[{"name":"탄수화물","unit":"g","value":"132.2"},{"name":"단백질","unit":"g","value":"25.0"},{"name":"지방","unit":"g","value":"16.6"},{"name":"비타민A","unit":"R.E","value":"133.3"},{"name":"티아민","unit":"mg","value":"0.8"},{"name":"리보플라빈","unit":"mg","value":"0.4"},{"name":"비타민C","unit":"mg","value":"32.1"},{"name":"칼슘","unit":"mg","value":"257.7"},{"name":"철분","unit":"mg","value":"4.5"}],"modifiedAt":1759330800}},"21":{"2":{"name":"중식","people":"797","menus":[{"name":"짜장라이스","allergy":[5,6,10,13,16]},{"name":"얼큰우렁된장국","allergy":[5,6]},{"name":"멸치볶음"},{"name":"매콤닭다리오븐구이","allergy":[5,6,12,13,15]},{"name":"반달단무지"},{"name":"배추김치","allergy":[9]},{"name":"애플망고쥬스","allergy":[13]}],"origin":[{"name":"쇠고기(종류)","origin":"국내산(한우)"},{"name":"쇠고기 식육가공품","origin":"국내산"},{"name":"돼지고기","origin":"국내산"},{"name":"돼지고기 식육가공품","origin":"국내산"},{"name":"닭고기","origin":"국내산"},{"name":"닭고기 식육가공품","origin":"국내산"},{"name":"오리고기","origin":"국내산"},{"name":"오리고기 가공품","origin":"국내산"},{"name":"양고기","origin":"해당없음"},{"name":"양고기 식육가공품","origin":"사용안함"},{"name":"쌀","origin":"국내산"},{"name":"쌀 가공품","origin":"국내산"},{"name":"배추","origin":"국내산"},{"name":"배추 가공품","origin":"국내산"},{"name":"고춧가루","origin":"국내산"},{"name":"고춧가루 가공품","origin":"국내산"},{"name":"콩","origin":"국내산"},{"name":"콩 가공품","origin":"국내산"},{"name":"넙치","origin":"국내산"},{"name":"넙치 수산가공품","origin":"국내산"},{"name":"조피볼락 수산가공품","origin":"국내산"},{"name":"조피볼락","origin":"국내산"},{"name":"참돔","origin":"국내산"},{"name":"참돔 수산가공품","origin":"국내산"},{"name":"미꾸라지","origin":"국내산"},{"name":"미꾸라지 수산가공품","origin":"국내산"},{"name":"뱀장어","origin":"사용안함"},{"name":"뱀장어 수산가공품","origin":"사용안함"},{"name":"낙지","origin":"중국산"},{"name":"낙지 수산가공품","origin":"사용안함"},{"name":"명태","origin":"미국산 ,러시아산"},{"name":"명태 수산가공품","origin":"미국산 ,러시아산"},{"name":"고등어","origin":"국내산"},{"name":"고등어 수산가공품","origin":"국내산"},{"name":"갈치","origin":"중국산"},{"name":"갈치 수산가공품","origin":"해당없음"},{"name":"오징어","origin":"국내산"},{"name":"오징어 수산가공품","origin":"국내산"},{"name":"꽃게 수산가공품","origin":"해당없음"},{"name":"꽃게","origin":"국내산"},{"name":"참조기","origin":"국내산"},{"name":"참조기 수산가공품","origin":"해당없음"},{"name":"다랑어","origin":"국내산"},{"name":"다랑어 수산가공품","origin":"해당없음"},{"name":"아귀","origin":"국내산"},{"name":"아귀 수산가공품","origin":"해당없음"},{"name":"주꾸미","origin":"국내산"},{"name":"주꾸미 수산가공품","origin":"해당없음"},{"name":"가리비","origin":"국내산"},{"name":"가리비 수산가공품","origin":"해당없음"},{"name":"우렁쉥이","origin":"국내산"},{"name":"우렁쉥이 수산가공품","origin":"해당없음"},{"name":"전복","origin":"국내산"},{"name":"전복 수산가공품","origin":"해당없음"},{"name":"방어","origin":"국내산"},{"name":"방어 수산가공품","origin":"해당없음"},{"name":"부세","origin":"국내산"},{"name":"부세 수산가공품","origin":"해당없음"},{"name":"비고","origin":""}],"calorie":"851.9 Kcal","nutrition":[{"name":"탄수화물","unit":"g","value":"94.9"},{"name":"단백질","unit":"g","value":"50.2"},{"name":"지방","unit":"g","value":"27.1"},{"name":"비타민A","unit":"R.E","value":"159.0"},{"name":"티아민","unit":"mg","value":"0.6"},{"name":"리보플라빈","unit":"mg","value":"0.4"},{"name":"비타민C","unit":"mg","value":"26.1"},{"name":"칼슘","unit":"mg","value":"188.2"},{"name":"철분","unit":"mg","value":"2.6"}],"modifiedAt":1759330800}},"22":{"2":{"name":"중식","people":"797","menus":[{"name":"유기농흑미밥"},{"name":"마라탕","allergy":[1,2,5,6,9,10,13,15,16,17,18]},{"name":"도토리묵무침","allergy":[5,6]},{"name":"꿔바로우탕수육\/새콤소스*","allergy":[1,5,6,10,11,12,13]},{"name":"배추김치","allergy":[9]},{"name":"스위트콘치즈","allergy":[1,2,5,13]},{"name":"유기농요구르트*","allergy":[2]}],"origin":[{"name":"쇠고기(종류)","origin":"국내산(한우)"},{"name":"쇠고기 식육가공품","origin":"국내산"},{"name":"돼지고기","origin":"국내산"},{"name":"돼지고기 식육가공품","origin":"국내산"},{"name":"닭고기","origin":"국내산"},{"name":"닭고기 식육가공품","origin":"국내산"},{"name":"오리고기","origin":"국내산"},{"name":"오리고기 가공품","origin":"국내산"},{"name":"양고기","origin":"해당없음"},{"name":"양고기 식육가공품","origin":"사용안함"},{"name":"쌀","origin":"국내산"},{"name":"쌀 가공품","origin":"국내산"},{"name":"배추","origin":"국내산"},{"name":"배추 가공품","origin":"국내산"},{"name":"고춧가루","origin":"국내산"},{"name":"고춧가루 가공품","origin":"국내산"},{"name":"콩","origin":"국내산"},{"name":"콩 가공품","origin":"국내산"},{"name":"넙치","origin":"국내산"},{"name":"넙치 수산가공품","origin":"국내산"},{"name":"조피볼락 수산가공품","origin":"국내산"},{"name":"조피볼락","origin":"국내산"},{"name":"참돔","origin":"국내산"},{"name":"참돔 수산가공품","origin":"국내산"},{"name":"미꾸라지","origin":"국내산"},{"name":"미꾸라지 수산가공품","origin":"국내산"},{"name":"뱀장어","origin":"사용안함"},{"name":"뱀장어 수산가공품","origin":"사용안함"},{"name":"낙지","origin":"중국산"},{"name":"낙지 수산가공품","origin":"사용안함"},{"name":"명태","origin":"미국산 ,러시아산"},{"name":"명태 수산가공품","origin":"미국산 ,러시아산"},{"name":"고등어","origin":"국내산"},{"name":"고등어 수산가공품","origin":"국내산"},{"name":"갈치","origin":"중국산"},{"name":"갈치 수산가공품","origin":"해당없음"},{"name":"오징어","origin":"국내산"},{"name":"오징어 수산가공품","origin":"국내산"},{"name":"꽃게 수산가공품","origin":"해당없음"},{"name":"꽃게","origin":"국내산"},{"name":"참조기","origin":"국내산"},{"name":"참조기 수산가공품","origin":"해당없음"},{"name":"다랑어","origin":"국내산"},{"name":"다랑어 수산가공품","origin":"해당없음"},{"name":"아귀","origin":"국내산"},{"name":"아귀 수산가공품","origin":"해당없음"},{"name":"주꾸미","origin":"국내산"},{"name":"주꾸미 수산가공품","origin":"해당없음"},{"name":"가리비","origin":"국내산"},{"name":"가리비 수산가공품","origin":"해당없음"},{"name":"우렁쉥이","origin":"국내산"},{"name":"우렁쉥이 수산가공품","origin":"해당없음"},{"name":"전복","origin":"국내산"},{"name":"전복 수산가공품","origin":"해당없음"},{"name":"방어","origin":"국내산"},{"name":"방어 수산가공품","origin":"해당없음"},{"name":"부세","origin":"국내산"},{"name":"부세 수산가공품","origin":"해당없음"},{"name":"비고","origin":""}],"calorie":"972.9 Kcal","nutrition":[{"name":"탄수화물","unit":"g","value":"145.8"},{"name":"단백질","unit":"g","value":"23.7"},{"name":"지방","unit":"g","value":"32.8"},{"name":"비타민A","unit":"R.E","value":"122.8"},{"name":"티아민","unit":"mg","value":"0.3"},{"name":"리보플라빈","unit":"mg","value":"0.4"},{"name":"비타민C","unit":"mg","value":"24.0"},{"name":"칼슘","unit":"mg","value":"251.7"},{"name":"철분","unit":"mg","value":"2.2"}],"modifiedAt":1759330800}},"23":{"2":{"name":"중식","people":"797","menus":[{"name":"유기농현미밥"},{"name":"북어포계란국","allergy":[1]},{"name":"도라지오이초무침","allergy":[5,6,13]},{"name":"숯불매콤돈육불고기","allergy":[5,6,10,12,13]},{"name":"치킨너겟&허니머스터드","allergy":[1,2,5,6,15]},{"name":"배추김치","allergy":[9]},{"name":"호박설기떡"}],"origin":[{"name":"쇠고기(종류)","origin":"국내산(한우)"},{"name":"쇠고기 식육가공품","origin":"국내산"},{"name":"돼지고기","origin":"국내산"},{"name":"돼지고기 식육가공품","origin":"국내산"},{"name":"닭고기","origin":"국내산"},{"name":"닭고기 식육가공품","origin":"국내산"},{"name":"오리고기","origin":"국내산"},{"name":"오리고기 가공품","origin":"국내산"},{"name":"양고기","origin":"해당없음"},{"name":"양고기 식육가공품","origin":"사용안함"},{"name":"쌀","origin":"국내산"},{"name":"쌀 가공품","origin":"국내산"},{"name":"배추","origin":"국내산"},{"name":"배추 가공품","origin":"국내산"},{"name":"고춧가루","origin":"국내산"},{"name":"고춧가루 가공품","origin":"국내산"},{"name":"콩","origin":"국내산"},{"name":"콩 가공품","origin":"국내산"},{"name":"넙치","origin":"국내산"},{"name":"넙치 수산가공품","origin":"국내산"},{"name":"조피볼락 수산가공품","origin":"국내산"},{"name":"조피볼락","origin":"국내산"},{"name":"참돔","origin":"국내산"},{"name":"참돔 수산가공품","origin":"국내산"},{"name":"미꾸라지","origin":"국내산"},{"name":"미꾸라지 수산가공품","origin":"국내산"},{"name":"뱀장어","origin":"사용안함"},{"name":"뱀장어 수산가공품","origin":"사용안함"},{"name":"낙지","origin":"중국산"},{"name":"낙지 수산가공품","origin":"사용안함"},{"name":"명태","origin":"미국산 ,러시아산"},{"name":"명태 수산가공품","origin":"미국산 ,러시아산"},{"name":"고등어","origin":"국내산"},{"name":"고등어 수산가공품","origin":"국내산"},{"name":"갈치","origin":"중국산"},{"name":"갈치 수산가공품","origin":"해당없음"},{"name":"오징어","origin":"국내산"},{"name":"오징어 수산가공품","origin":"국내산"},{"name":"꽃게 수산가공품","origin":"해당없음"},{"name":"꽃게","origin":"국내산"},{"name":"참조기","origin":"국내산"},{"name":"참조기 수산가공품","origin":"해당없음"},{"name":"다랑어","origin":"국내산"},{"name":"다랑어 수산가공품","origin":"해당없음"},{"name":"아귀","origin":"국내산"},{"name":"아귀 수산가공품","origin":"해당없음"},{"name":"주꾸미","origin":"국내산"},{"name":"주꾸미 수산가공품","origin":"해당없음"},{"name":"가리비","origin":"국내산"},{"name":"가리비 수산가공품","origin":"해당없음"},{"name":"우렁쉥이","origin":"국내산"},{"name":"우렁쉥이 수산가공품","origin":"해당없음"},{"name":"전복","origin":"국내산"},{"name":"전복 수산가공품","origin":"해당없음"},{"name":"방어","origin":"국내산"},{"name":"방어 수산가공품","origin":"해당없음"},{"name":"부세","origin":"국내산"},{"name":"부세 수산가공품","origin":"해당없음"},{"name":"비고","origin":""}],"calorie":"914.2 Kcal","nutrition":[{"name":"탄수화물","unit":"g","value":"113.1"},{"name":"단백질","unit":"g","value":"42.7"},{"name":"지방","unit":"g","value":"30.3"},{"name":"비타민A","unit":"R.E","value":"80.4"},{"name":"티아민","unit":"mg","value":"1.0"},{"name":"리보플라빈","unit":"mg","value":"0.5"},{"name":"비타민C","unit":"mg","value":"8.6"},{"name":"칼슘","unit":"mg","value":"115.9"},{"name":"철분","unit":"mg","value":"2.8"}],"modifiedAt":1759330800}},"24":{"2":{"name":"중식","people":"797","menus":[{"name":"유기농잡곡밥","allergy":[5]},{"name":"참치찌개","allergy":[5,6,9,16,18]},{"name":"우리밀치킨까스.허니머스터드","allergy":[1,2,5,6,12,13,15]},{"name":"우엉채어묵조림","allergy":[1,5,6]},{"name":"브로콜리흑임자샐러드","allergy":[1,5,9,13]},{"name":"총각김치","allergy":[9]},{"name":"화이트애플파이","allergy":[1,2,5,6]}],"origin":[{"name":"쇠고기(종류)","origin":"국내산(한우)"},{"name":"쇠고기 식육가공품","origin":"국내산"},{"name":"돼지고기","origin":"국내산"},{"name":"돼지고기 식육가공품","origin":"국내산"},{"name":"닭고기","origin":"국내산"},{"name":"닭고기 식육가공품","origin":"국내산"},{"name":"오리고기","origin":"국내산"},{"name":"오리고기 가공품","origin":"국내산"},{"name":"양고기","origin":"해당없음"},{"name":"양고기 식육가공품","origin":"사용안함"},{"name":"쌀","origin":"국내산"},{"name":"쌀 가공품","origin":"국내산"},{"name":"배추","origin":"국내산"},{"name":"배추 가공품","origin":"국내산"},{"name":"고춧가루","origin":"국내산"},{"name":"고춧가루 가공품","origin":"국내산"},{"name":"콩","origin":"국내산"},{"name":"콩 가공품","origin":"국내산"},{"name":"넙치","origin":"국내산"},{"name":"넙치 수산가공품","origin":"국내산"},{"name":"조피볼락 수산가공품","origin":"국내산"},{"name":"조피볼락","origin":"국내산"},{"name":"참돔","origin":"국내산"},{"name":"참돔 수산가공품","origin":"국내산"},{"name":"미꾸라지","origin":"국내산"},{"name":"미꾸라지 수산가공품","origin":"국내산"},{"name":"뱀장어","origin":"사용안함"},{"name":"뱀장어 수산가공품","origin":"사용안함"},{"name":"낙지","origin":"중국산"},{"name":"낙지 수산가공품","origin":"사용안함"},{"name":"명태","origin":"미국산 ,러시아산"},{"name":"명태 수산가공품","origin":"미국산 ,러시아산"},{"name":"고등어","origin":"국내산"},{"name":"고등어 수산가공품","origin":"국내산"},{"name":"갈치","origin":"중국산"},{"name":"갈치 수산가공품","origin":"해당없음"},{"name":"오징어","origin":"국내산"},{"name":"오징어 수산가공품","origin":"국내산"},{"name":"꽃게 수산가공품","origin":"해당없음"},{"name":"꽃게","origin":"국내산"},{"name":"참조기","origin":"국내산"},{"name":"참조기 수산가공품","origin":"해당없음"},{"name":"다랑어","origin":"국내산"},{"name":"다랑어 수산가공품","origin":"해당없음"},{"name":"아귀","origin":"국내산"},{"name":"아귀 수산가공품","origin":"해당없음"},{"name":"주꾸미","origin":"국내산"},{"name":"주꾸미 수산가공품","origin":"해당없음"},{"name":"가리비","origin":"국내산"},{"name":"가리비 수산가공품","origin":"해당없음"},{"name":"우렁쉥이","origin":"국내산"},{"name":"우렁쉥이 수산가공품","origin":"해당없음"},{"name":"전복","origin":"국내산"},{"name":"전복 수산가공품","origin":"해당없음"},{"name":"방어","origin":"국내산"},{"name":"방어 수산가공품","origin":"해당없음"},{"name":"부세","origin":"국내산"},{"name":"부세 수산가공품","origin":"해당없음"},{"name":"비고","origin":""}],"calorie":"725.7 Kcal","nutrition":[{"name":"탄수화물","unit":"g","value":"94.3"},{"name":"단백질","unit":"g","value":"29.7"},{"name":"지방","unit":"g","value":"24.8"},{"name":"비타민A","unit":"R.E","value":"45.2"},{"name":"티아민","unit":"mg","value":"0.3"},{"name":"리보플라빈","unit":"mg","value":"0.3"},{"name":"비타민C","unit":"mg","value":"7.4"},{"name":"칼슘","unit":"mg","value":"84.4"},{"name":"철분","unit":"mg","value":"2.0"}],"modifiedAt":1759330800}},"27":{"2":{"name":"중식","people":"797","menus":[{"name":"유기농현미밥"},{"name":"청국장찌개","allergy":[5,9]},{"name":"매콤닭살떡조림","allergy":[1,5,6,12,13,15]},{"name":"시금치나물"},{"name":"갈치카레구이","allergy":[2,5,6,12,13,16,18]},{"name":"배추김치","allergy":[9]},{"name":"딸바라떼","allergy":[2,13]}],"origin":[{"name":"쇠고기(종류)","origin":"국내산(한우)"},{"name":"쇠고기 식육가공품","origin":"국내산"},{"name":"돼지고기","origin":"국내산"},{"name":"돼지고기 식육가공품","origin":"국내산"},{"name":"닭고기","origin":"국내산"},{"name":"닭고기 식육가공품","origin":"국내산"},{"name":"오리고기","origin":"국내산"},{"name":"오리고기 가공품","origin":"국내산"},{"name":"양고기","origin":"해당없음"},{"name":"양고기 식육가공품","origin":"사용안함"},{"name":"쌀","origin":"국내산"},{"name":"쌀 가공품","origin":"국내산"},{"name":"배추","origin":"국내산"},{"name":"배추 가공품","origin":"국내산"},{"name":"고춧가루","origin":"국내산"},{"name":"고춧가루 가공품","origin":"국내산"},{"name":"콩","origin":"국내산"},{"name":"콩 가공품","origin":"국내산"},{"name":"넙치","origin":"국내산"},{"name":"넙치 수산가공품","origin":"국내산"},{"name":"조피볼락 수산가공품","origin":"국내산"},{"name":"조피볼락","origin":"국내산"},{"name":"참돔","origin":"국내산"},{"name":"참돔 수산가공품","origin":"국내산"},{"name":"미꾸라지","origin":"국내산"},{"name":"미꾸라지 수산가공품","origin":"국내산"},{"name":"뱀장어","origin":"사용안함"},{"name":"뱀장어 수산가공품","origin":"사용안함"},{"name":"낙지","origin":"중국산"},{"name":"낙지 수산가공품","origin":"사용안함"},{"name":"명태","origin":"미국산 ,러시아산"},{"name":"명태 수산가공품","origin":"미국산 ,러시아산"},{"name":"고등어","origin":"국내산"},{"name":"고등어 수산가공품","origin":"국내산"},{"name":"갈치","origin":"중국산"},{"name":"갈치 수산가공품","origin":"해당없음"},{"name":"오징어","origin":"국내산"},{"name":"오징어 수산가공품","origin":"국내산"},{"name":"꽃게 수산가공품","origin":"해당없음"},{"name":"꽃게","origin":"국내산"},{"name":"참조기","origin":"국내산"},{"name":"참조기 수산가공품","origin":"해당없음"},{"name":"다랑어","origin":"국내산"},{"name":"다랑어 수산가공품","origin":"해당없음"},{"name":"아귀","origin":"국내산"},{"name":"아귀 수산가공품","origin":"해당없음"},{"name":"주꾸미","origin":"국내산"},{"name":"주꾸미 수산가공품","origin":"해당없음"},{"name":"가리비","origin":"국내산"},{"name":"가리비 수산가공품","origin":"해당없음"},{"name":"우렁쉥이","origin":"국내산"},{"name":"우렁쉥이 수산가공품","origin":"해당없음"},{"name":"전복","origin":"국내산"},{"name":"전복 수산가공품","origin":"해당없음"},{"name":"방어","origin":"국내산"},{"name":"방어 수산가공품","origin":"해당없음"},{"name":"부세","origin":"국내산"},{"name":"부세 수산가공품","origin":"해당없음"},{"name":"비고","origin":""}],"calorie":"742.6 Kcal","nutrition":[{"name":"탄수화물","unit":"g","value":"100.5"},{"name":"단백질","unit":"g","value":"38.4"},{"name":"지방","unit":"g","value":"19.4"},{"name":"비타민A","unit":"R.E","value":"199.1"},{"name":"티아민","unit":"mg","value":"0.5"},{"name":"리보플라빈","unit":"mg","value":"0.6"},{"name":"비타민C","unit":"mg","value":"22.2"},{"name":"칼슘","unit":"mg","value":"180.5"},{"name":"철분","unit":"mg","value":"3.5"}],"modifiedAt":1759330800}},"28":{"2":{"name":"중식","people":"797","menus":[{"name":"유기농귀리밥"},{"name":"김치수제비국","allergy":[5,6,9,13]},{"name":"회오리감자","allergy":[2,5,6,13]},{"name":"콩나물무침","allergy":[5]},{"name":"돈육안심떡찜","allergy":[5,6,10,13,18]},{"name":"우리콩두부조림","allergy":[5,6]},{"name":"깍두기","allergy":[9]}],"origin":[{"name":"쇠고기(종류)","origin":"국내산(한우)"},{"name":"쇠고기 식육가공품","origin":"국내산"},{"name":"돼지고기","origin":"국내산"},{"name":"돼지고기 식육가공품","origin":"국내산"},{"name":"닭고기","origin":"국내산"},{"name":"닭고기 식육가공품","origin":"국내산"},{"name":"오리고기","origin":"국내산"},{"name":"오리고기 가공품","origin":"국내산"},{"name":"양고기","origin":"해당없음"},{"name":"양고기 식육가공품","origin":"사용안함"},{"name":"쌀","origin":"국내산"},{"name":"쌀 가공품","origin":"국내산"},{"name":"배추","origin":"국내산"},{"name":"배추 가공품","origin":"국내산"},{"name":"고춧가루","origin":"국내산"},{"name":"고춧가루 가공품","origin":"국내산"},{"name":"콩","origin":"국내산"},{"name":"콩 가공품","origin":"국내산"},{"name":"넙치","origin":"국내산"},{"name":"넙치 수산가공품","origin":"국내산"},{"name":"조피볼락 수산가공품","origin":"국내산"},{"name":"조피볼락","origin":"국내산"},{"name":"참돔","origin":"국내산"},{"name":"참돔 수산가공품","origin":"국내산"},{"name":"미꾸라지","origin":"국내산"},{"name":"미꾸라지 수산가공품","origin":"국내산"},{"name":"뱀장어","origin":"사용안함"},{"name":"뱀장어 수산가공품","origin":"사용안함"},{"name":"낙지","origin":"중국산"},{"name":"낙지 수산가공품","origin":"사용안함"},{"name":"명태","origin":"미국산 ,러시아산"},{"name":"명태 수산가공품","origin":"미국산 ,러시아산"},{"name":"고등어","origin":"국내산"},{"name":"고등어 수산가공품","origin":"국내산"},{"name":"갈치","origin":"중국산"},{"name":"갈치 수산가공품","origin":"해당없음"},{"name":"오징어","origin":"국내산"},{"name":"오징어 수산가공품","origin":"국내산"},{"name":"꽃게 수산가공품","origin":"해당없음"},{"name":"꽃게","origin":"국내산"},{"name":"참조기","origin":"국내산"},{"name":"참조기 수산가공품","origin":"해당없음"},{"name":"다랑어","origin":"국내산"},{"name":"다랑어 수산가공품","origin":"해당없음"},{"name":"아귀","origin":"국내산"},{"name":"아귀 수산가공품","origin":"해당없음"},{"name":"주꾸미","origin":"국내산"},{"name":"주꾸미 수산가공품","origin":"해당없음"},{"name":"가리비","origin":"국내산"},{"name":"가리비 수산가공품","origin":"해당없음"},{"name":"우렁쉥이","origin":"국내산"},{"name":"우렁쉥이 수산가공품","origin":"해당없음"},{"name":"전복","origin":"국내산"},{"name":"전복 수산가공품","origin":"해당없음"},{"name":"방어","origin":"국내산"},{"name":"방어 수산가공품","origin":"해당없음"},{"name":"부세","origin":"국내산"},{"name":"부세 수산가공품","origin":"해당없음"},{"name":"비고","origin":""}],"calorie":"852.8 Kcal","nutrition":[{"name":"탄수화물","unit":"g","value":"126.1"},{"name":"단백질","unit":"g","value":"40.2"},{"name":"지방","unit":"g","value":"19.4"},{"name":"비타민A","unit":"R.E","value":"89.5"},{"name":"티아민","unit":"mg","value":"1.1"},{"name":"리보플라빈","unit":"mg","value":"0.7"},{"name":"비타민C","unit":"mg","value":"15.8"},{"name":"칼슘","unit":"mg","value":"174.1"},{"name":"철분","unit":"mg","value":"3.9"}],"modifiedAt":1759330800}},"29":{"2":{"name":"중식","people":"797","menus":[{"name":"유기농강황밥"},{"name":"모듬어묵국","allergy":[1,5,6,13]},{"name":"롱새우튀김","allergy":[1,5,6,9]},{"name":"단무지맛살냉채","allergy":[1,5,6,8,13]},{"name":"배추김치","allergy":[9]},{"name":"치즈떡볶이","allergy":[1,2,5,6,13]},{"name":"샤인머스켓"}],"origin":[{"name":"쇠고기(종류)","origin":"국내산(한우)"},{"name":"쇠고기 식육가공품","origin":"국내산"},{"name":"돼지고기","origin":"국내산"},{"name":"돼지고기 식육가공품","origin":"국내산"},{"name":"닭고기","origin":"국내산"},{"name":"닭고기 식육가공품","origin":"국내산"},{"name":"오리고기","origin":"국내산"},{"name":"오리고기 가공품","origin":"국내산"},{"name":"양고기","origin":"해당없음"},{"name":"양고기 식육가공품","origin":"사용안함"},{"name":"쌀","origin":"국내산"},{"name":"쌀 가공품","origin":"국내산"},{"name":"배추","origin":"국내산"},{"name":"배추 가공품","origin":"국내산"},{"name":"고춧가루","origin":"국내산"},{"name":"고춧가루 가공품","origin":"국내산"},{"name":"콩","origin":"국내산"},{"name":"콩 가공품","origin":"국내산"},{"name":"넙치","origin":"국내산"},{"name":"넙치 수산가공품","origin":"국내산"},{"name":"조피볼락 수산가공품","origin":"국내산"},{"name":"조피볼락","origin":"국내산"},{"name":"참돔","origin":"국내산"},{"name":"참돔 수산가공품","origin":"국내산"},{"name":"미꾸라지","origin":"국내산"},{"name":"미꾸라지 수산가공품","origin":"국내산"},{"name":"뱀장어","origin":"사용안함"},{"name":"뱀장어 수산가공품","origin":"사용안함"},{"name":"낙지","origin":"중국산"},{"name":"낙지 수산가공품","origin":"사용안함"},{"name":"명태","origin":"미국산 ,러시아산"},{"name":"명태 수산가공품","origin":"미국산 ,러시아산"},{"name":"고등어","origin":"국내산"},{"name":"고등어 수산가공품","origin":"국내산"},{"name":"갈치","origin":"중국산"},{"name":"갈치 수산가공품","origin":"해당없음"},{"name":"오징어","origin":"국내산"},{"name":"오징어 수산가공품","origin":"국내산"},{"name":"꽃게 수산가공품","origin":"해당없음"},{"name":"꽃게","origin":"국내산"},{"name":"참조기","origin":"국내산"},{"name":"참조기 수산가공품","origin":"해당없음"},{"name":"다랑어","origin":"국내산"},{"name":"다랑어 수산가공품","origin":"해당없음"},{"name":"아귀","origin":"국내산"},{"name":"아귀 수산가공품","origin":"해당없음"},{"name":"주꾸미","origin":"국내산"},{"name":"주꾸미 수산가공품","origin":"해당없음"},{"name":"가리비","origin":"국내산"},{"name":"가리비 수산가공품","origin":"해당없음"},{"name":"우렁쉥이","origin":"국내산"},{"name":"우렁쉥이 수산가공품","origin":"해당없음"},{"name":"전복","origin":"국내산"},{"name":"전복 수산가공품","origin":"해당없음"},{"name":"방어","origin":"국내산"},{"name":"방어 수산가공품","origin":"해당없음"},{"name":"부세","origin":"국내산"},{"name":"부세 수산가공품","origin":"해당없음"},{"name":"비고","origin":""}],"calorie":"752.0 Kcal","nutrition":[{"name":"탄수화물","unit":"g","value":"135.2"},{"name":"단백질","unit":"g","value":"19.9"},{"name":"지방","unit":"g","value":"14.3"},{"name":"비타민A","unit":"R.E","value":"36.8"},{"name":"티아민","unit":"mg","value":"0.2"},{"name":"리보플라빈","unit":"mg","value":"0.1"},{"name":"비타민C","unit":"mg","value":"17.6"},{"name":"칼슘","unit":"mg","value":"204.9"},{"name":"철분","unit":"mg","value":"1.6"}],"modifiedAt":1759330800}},"30":{"2":{"name":"중식","people":"797","menus":[{"name":"유기농현미밥"},{"name":"바지락순두부찌개","allergy":[5,9,10,13,18]},{"name":"삼치무조림","allergy":[5,6,13]},{"name":"오리훈제채소무침","allergy":[1,2,3,5,6,13]},{"name":"치커리상추겉절이"},{"name":"배추김치","allergy":[9]},{"name":"대추방울토마토","allergy":[12]}],"origin":[{"name":"쇠고기(종류)","origin":"국내산(한우)"},{"name":"쇠고기 식육가공품","origin":"국내산"},{"name":"돼지고기","origin":"국내산"},{"name":"돼지고기 식육가공품","origin":"국내산"},{"name":"닭고기","origin":"국내산"},{"name":"닭고기 식육가공품","origin":"국내산"},{"name":"오리고기","origin":"국내산"},{"name":"오리고기 가공품","origin":"국내산"},{"name":"양고기","origin":"해당없음"},{"name":"양고기 식육가공품","origin":"사용안함"},{"name":"쌀","origin":"국내산"},{"name":"쌀 가공품","origin":"국내산"},{"name":"배추","origin":"국내산"},{"name":"배추 가공품","origin":"국내산"},{"name":"고춧가루","origin":"국내산"},{"name":"고춧가루 가공품","origin":"국내산"},{"name":"콩","origin":"국내산"},{"name":"콩 가공품","origin":"국내산"},{"name":"넙치","origin":"국내산"},{"name":"넙치 수산가공품","origin":"국내산"},{"name":"조피볼락 수산가공품","origin":"국내산"},{"name":"조피볼락","origin":"국내산"},{"name":"참돔","origin":"국내산"},{"name":"참돔 수산가공품","origin":"국내산"},{"name":"미꾸라지","origin":"국내산"},{"name":"미꾸라지 수산가공품","origin":"국내산"},{"name":"뱀장어","origin":"사용안함"},{"name":"뱀장어 수산가공품","origin":"사용안함"},{"name":"낙지","origin":"중국산"},{"name":"낙지 수산가공품","origin":"사용안함"},{"name":"명태","origin":"미국산 ,러시아산"},{"name":"명태 수산가공품","origin":"미국산 ,러시아산"},{"name":"고등어","origin":"국내산"},{"name":"고등어 수산가공품","origin":"국내산"},{"name":"갈치","origin":"중국산"},{"name":"갈치 수산가공품","origin":"해당없음"},{"name":"오징어","origin":"국내산"},{"name":"오징어 수산가공품","origin":"국내산"},{"name":"꽃게 수산가공품","origin":"해당없음"},{"name":"꽃게","origin":"국내산"},{"name":"참조기","origin":"국내산"},{"name":"참조기 수산가공품","origin":"해당없음"},{"name":"다랑어","origin":"국내산"},{"name":"다랑어 수산가공품","origin":"해당없음"},{"name":"아귀","origin":"국내산"},{"name":"아귀 수산가공품","origin":"해당없음"},{"name":"주꾸미","origin":"국내산"},{"name":"주꾸미 수산가공품","origin":"해당없음"},{"name":"가리비","origin":"국내산"},{"name":"가리비 수산가공품","origin":"해당없음"},{"name":"우렁쉥이","origin":"국내산"},{"name":"우렁쉥이 수산가공품","origin":"해당없음"},{"name":"전복","origin":"국내산"},{"name":"전복 수산가공품","origin":"해당없음"},{"name":"방어","origin":"국내산"},{"name":"방어 수산가공품","origin":"해당없음"},{"name":"부세","origin":"국내산"},{"name":"부세 수산가공품","origin":"해당없음"},{"name":"비고","origin":""}],"calorie":"758.6 Kcal","nutrition":[{"name":"탄수화물","unit":"g","value":"78.1"},{"name":"단백질","unit":"g","value":"35.2"},{"name":"지방","unit":"g","value":"33.2"},{"name":"비타민A","unit":"R.E","value":"162.9"},{"name":"티아민","unit":"mg","value":"0.7"},{"name":"리보플라빈","unit":"mg","value":"0.5"},{"name":"비타민C","unit":"mg","value":"47.3"},{"name":"칼슘","unit":"mg","value":"157.1"},{"name":"철분","unit":"mg","value":"2.9"}],"modifiedAt":1759330800}},"31":{"2":{"name":"중식","people":"797","menus":[{"name":"유기농율무밥"},{"name":"김치콩나물국","allergy":[5,6,9]},{"name":"돈육계란장조림","allergy":[1,5,6,10,13]},{"name":"오이부추무침","allergy":[5,6,13]},{"name":"스윗소코순살치킨*","allergy":[1,2,5,6,15]},{"name":"배추김치","allergy":[9]},{"name":"감귤쥬스","allergy":[13]}],"origin":[{"name":"쇠고기(종류)","origin":"국내산(한우)"},{"name":"쇠고기 식육가공품","origin":"국내산"},{"name":"돼지고기","origin":"국내산"},{"name":"돼지고기 식육가공품","origin":"국내산"},{"name":"닭고기","origin":"국내산"},{"name":"닭고기 식육가공품","origin":"국내산"},{"name":"오리고기","origin":"국내산"},{"name":"오리고기 가공품","origin":"국내산"},{"name":"쌀","origin":"국내산"},{"name":"배추","origin":"국내산"},{"name":"고춧가루","origin":"국내산"},{"name":"콩","origin":"국내산"},{"name":"낙지","origin":"국내산"},{"name":"고등어","origin":"국내산"},{"name":"갈치","origin":"국내산"},{"name":"오징어","origin":"국내산"},{"name":"꽃게","origin":"국내산"},{"name":"참조기","origin":"국내산"},{"name":"비고","origin":""}],"calorie":"637.5 Kcal","nutrition":[{"name":"탄수화물","unit":"g","value":"87.4"},{"name":"단백질","unit":"g","value":"37.4"},{"name":"지방","unit":"g","value":"14.6"},{"name":"비타민A","unit":"R.E","value":"51.6"},{"name":"티아민","unit":"mg","value":"0.8"},{"name":"리보플라빈","unit":"mg","value":"0.6"},{"name":"비타민C","unit":"mg","value":"24.9"},{"name":"칼슘","unit":"mg","value":"167.7"},{"name":"철분","unit":"mg","value":"3.3"}],"modifiedAt":1759330800}}}